gitex/__init__.py
gitex/dependency_mapper.py
gitex/docstring_extractor.py
gitex/main.py
gitex/models.py
gitex/renderer.py
gitex/utils.py
gitex/picker/__init__.py
gitex/picker/base.py
gitex/picker/questionary.py
gitex/picker/textuals.py
tests/test_cli.py
tests/test_fences.py
tests/test_render.py
tests/test_skip_binaries.py
tests/test_textual.py
gitex-0.2.19.dist-info/METADATA
gitex-0.2.19.dist-info/WHEEL
gitex-0.2.19.dist-info/entry_points.txt
gitex-0.2.19.dist-info/top_level.txt
gitex-0.2.19.dist-info/RECORD
