Metadata-Version: 2.4
Name: gitex
Version: 0.2.19
Summary: Terminal tool to prep codebases for LLMs
Author-email: zozaai <info@zozaai.com>
License: MIT
Requires-Python: >=3.9
Requires-Dist: click<8.2,>=8.0
Requires-Dist: textual>=5.2.0
Requires-Dist: questionary==2.1.0
Requires-Dist: pathspec<1.0,>=0.10.1
Requires-Dist: pydantic
Requires-Dist: GitPython
Provides-Extra: test
Requires-Dist: pytest>=8.0; extra == "test"
Requires-Dist: pytest-cov>=5.0; extra == "test"
Requires-Dist: pytest-asyncio; extra == "test"
